src/__init__.py
src/dataset.py
src/sdqc.py
src/util.py
src/verif.py
clearumor-1.0.1.dist-info/LICENSE
clearumor-1.0.1.dist-info/METADATA
clearumor-1.0.1.dist-info/NOTICE
clearumor-1.0.1.dist-info/WHEEL
clearumor-1.0.1.dist-info/dependency_links.txt
clearumor-1.0.1.dist-info/top_level.txt
clearumor-1.0.1.dist-info/RECORD
