Metadata-Version: 2.1
Name: clearumor
Version: 1.0.1
Summary: CLEARumor implementation
Home-page: https://github.com/Institute-Web-Science-and-Technologies/CLEARumor
License: Apache License 2.0
Platform: UNKNOWN
Classifier: Development Status :: 3 - Alpha
Requires-Python: >=3.6
